g4f/__init__.py
g4f/cli.py
g4f/cookies.py
g4f/debug.py
g4f/errors.py
g4f/image.py
g4f/models.py
g4f/stubs.py
g4f/typing.py
g4f/version.py
g4f/webdriver.py
g4f/Provider/AI365VIP.py
g4f/Provider/Allyfy.py
g4f/Provider/Aura.py
g4f/Provider/Bing.py
g4f/Provider/BingCreateImages.py
g4f/Provider/Blackbox.py
g4f/Provider/ChatGot.py
g4f/Provider/Chatgpt4Online.py
g4f/Provider/Chatgpt4o.py
g4f/Provider/ChatgptFree.py
g4f/Provider/Cohere.py
g4f/Provider/DDG.py
g4f/Provider/DeepInfra.py
g4f/Provider/DeepInfraImage.py
g4f/Provider/Feedough.py
g4f/Provider/FlowGpt.py
g4f/Provider/FreeChatgpt.py
g4f/Provider/FreeGpt.py
g4f/Provider/FreeNetfly.py
g4f/Provider/GeminiPro.py
g4f/Provider/GeminiProChat.py
g4f/Provider/GigaChat.py
g4f/Provider/GptTalkRu.py
g4f/Provider/HuggingChat.py
g4f/Provider/HuggingFace.py
g4f/Provider/Koala.py
g4f/Provider/Liaobots.py
g4f/Provider/LiteIcoding.py
g4f/Provider/Llama.py
g4f/Provider/Local.py
g4f/Provider/MagickPenAsk.py
g4f/Provider/MagickPenChat.py
g4f/Provider/Marsyoo.py
g4f/Provider/MetaAI.py
g4f/Provider/MetaAIAccount.py
g4f/Provider/Ollama.py
g4f/Provider/PerplexityLabs.py
g4f/Provider/Phind.py
g4f/Provider/Pi.py
g4f/Provider/Pizzagpt.py
g4f/Provider/Reka.py
g4f/Provider/Replicate.py
g4f/Provider/ReplicateHome.py
g4f/Provider/Rocks.py
g4f/Provider/TeachAnything.py
g4f/Provider/Vercel.py
g4f/Provider/WhiteRabbitNeo.py
g4f/Provider/You.py
g4f/Provider/__init__.py
g4f/Provider/base_provider.py
g4f/Provider/helper.py
g4f/Provider/bing/__init__.py
g4f/Provider/bing/conversation.py
g4f/Provider/bing/create_images.py
g4f/Provider/bing/upload_image.py
g4f/Provider/deprecated/Acytoo.py
g4f/Provider/deprecated/AiAsk.py
g4f/Provider/deprecated/AiChatOnline.py
g4f/Provider/deprecated/AiService.py
g4f/Provider/deprecated/Aibn.py
g4f/Provider/deprecated/Aichat.py
g4f/Provider/deprecated/Ails.py
g4f/Provider/deprecated/Aivvm.py
g4f/Provider/deprecated/Berlin.py
g4f/Provider/deprecated/ChatAnywhere.py
g4f/Provider/deprecated/ChatgptDuo.py
g4fu-10.3.2.4.dist-info/LICENSE
g4fu-10.3.2.4.dist-info/METADATA
g4fu-10.3.2.4.dist-info/WHEEL
g4fu-10.3.2.4.dist-info/entry_points.txt
g4fu-10.3.2.4.dist-info/top_level.txt
g4fu-10.3.2.4.dist-info/RECORD
