Metadata-Version: 2.1
Name: g4fu
Version: 10.3.2.4
Summary: Fork of the gpt4free repository | EDUCATIONAL PURPOSES ONLY | various collection of powerful language models
Home-page: https://github.com/XInTheDark/gpt4free-u
Author: XInTheDark
Author-email: <muzhengaming@gmail.com>
Project-URL: Source Code, https://github.com/XInTheDark/gpt4free-u
Project-URL: Bug Tracker, https://github.com/XInTheDark/gpt4free-u/issues
Keywords: python,chatbot,reverse-engineering,openai,chatbots,gpt,language-model,gpt-3,gpt3,openai-api,gpt-4,gpt4,chatgpt,chatgpt-api,openai-chatgpt,chatgpt-free,chatgpt-4,chatgpt4,chatgpt4-api,free,free-gpt,gpt4free,g4f
Classifier: Development Status :: 2 - Pre-Alpha
Classifier: Intended Audience :: Developers
Classifier: Programming Language :: Python :: 3
Classifier: Operating System :: Unix
Classifier: Operating System :: MacOS :: MacOS X
Classifier: Operating System :: Microsoft :: Windows
License-File: LICENSE
Requires-Dist: requests
Requires-Dist: aiohttp
Requires-Dist: brotli
Requires-Dist: pycryptodome
Provides-Extra: all
Requires-Dist: curl-cffi >=0.6.2 ; extra == 'all'
Requires-Dist: certifi ; extra == 'all'
Requires-Dist: browser-cookie3 ; extra == 'all'
Requires-Dist: PyExecJS ; extra == 'all'
Requires-Dist: duckduckgo-search >=5.0 ; extra == 'all'
Requires-Dist: beautifulsoup4 ; extra == 'all'
Requires-Dist: brotli ; extra == 'all'
Requires-Dist: nodriver ; extra == 'all'
Requires-Dist: pywebview ; extra == 'all'
Requires-Dist: platformdirs ; extra == 'all'
Requires-Dist: plyer ; extra == 'all'
Requires-Dist: cryptography ; extra == 'all'
Requires-Dist: aiohttp-socks ; extra == 'all'
Requires-Dist: pillow ; extra == 'all'
Requires-Dist: cairosvg ; extra == 'all'
Requires-Dist: werkzeug ; extra == 'all'
Requires-Dist: flask ; extra == 'all'
Requires-Dist: loguru ; extra == 'all'
Requires-Dist: fastapi ; extra == 'all'
Requires-Dist: uvicorn ; extra == 'all'
Requires-Dist: nest-asyncio ; extra == 'all'
Requires-Dist: pycryptodome ; extra == 'all'
Provides-Extra: api
Requires-Dist: loguru ; extra == 'api'
Requires-Dist: fastapi ; extra == 'api'
Requires-Dist: uvicorn ; extra == 'api'
Requires-Dist: nest-asyncio ; extra == 'api'
Provides-Extra: curl_cffi
Requires-Dist: curl-cffi >=0.6.2 ; extra == 'curl_cffi'
Provides-Extra: gui
Requires-Dist: werkzeug ; extra == 'gui'
Requires-Dist: flask ; extra == 'gui'
Requires-Dist: beautifulsoup4 ; extra == 'gui'
Requires-Dist: pillow ; extra == 'gui'
Requires-Dist: duckduckgo-search >=5.0 ; extra == 'gui'
Requires-Dist: browser-cookie3 ; extra == 'gui'
Provides-Extra: image
Requires-Dist: pillow ; extra == 'image'
Requires-Dist: cairosvg ; extra == 'image'
Requires-Dist: beautifulsoup4 ; extra == 'image'
Provides-Extra: local
Requires-Dist: gpt4all ; extra == 'local'
Provides-Extra: openai
Requires-Dist: pycryptodome ; extra == 'openai'
Provides-Extra: webdriver
Requires-Dist: platformdirs ; extra == 'webdriver'
Requires-Dist: undetected-chromedriver >=3.5.5 ; extra == 'webdriver'
Requires-Dist: setuptools ; extra == 'webdriver'
Requires-Dist: selenium-wire ; extra == 'webdriver'
Provides-Extra: webview
Requires-Dist: webview ; extra == 'webview'
Requires-Dist: platformdirs ; extra == 'webview'
Requires-Dist: plyer ; extra == 'webview'
Requires-Dist: cryptography ; extra == 'webview'
